[
  {
      "id": 1,
      "title": "HP ProDesk 400 G7",
      "price": "12.000.000₫",
      "rating": "★★★★☆",
      "image": "https://tse2.mm.bing.net/th?id=OIP.Rnv_bULlsgAF1Z0grshrRwHaFy&pid=Api",
      "alt": "HP ProDesk 400 G7",
      "description": "Bộ vi xử lý: Intel Core i5-10500, RAM: 8GB DDR4, Ổ cứng: SSD 256GB."
  },
  {
      "id": 2,
      "title": "Dell OptiPlex 3080",
      "price": "13.500.000₫",
      "rating": "★★★★☆",
      "image": "https://tse3.mm.bing.net/th?id=OIP.RFwHhQ9UxB2Xq60sPUuF3gHaHa&pid=Api",
      "alt": "Dell OptiPlex 3080",
      "description": "Bộ vi xử lý: Intel Core i5-10500, RAM: 8GB DDR4, Ổ cứng: SSD 256GB."
  },
  {
      "id": 3,
      "title": "Lenovo ThinkCentre M720s",
      "price": "12.500.000₫",
      "rating": "★★★★☆",
      "image": "https://tse1.mm.bing.net/th?id=OIP.88jn1ICTUgBs8yVdq6ZMlwHaHa&pid=Api",
      "alt": "Lenovo ThinkCentre M720s",
      "description": "Bộ vi xử lý: Intel Core i5-10500, RAM: 8GB DDR4, Ổ cứng: SSD 256GB."
  },
  {
      "id": 4,
      "title": "Acer Veriton X",
      "price": "11.000.000₫",
      "rating": "★★★☆☆",
      "image": "https://tse3.mm.bing.net/th?id=OIP.N0xFOcnhNy5P0RKX1mCQ4gHaHa&pid=Api",
      "alt": "Acer Veriton X",
      "description": "Bộ vi xử lý: Intel Core i5-10500, RAM: 8GB DDR4, Ổ cứng: SSD 256GB."
  },
  {
      "id": 5,
      "title": "Asus ExpertCenter D500SA",
      "price": "12.000.000₫",
      "rating": "★★★★☆",
      "image": "https://tse1.mm.bing.net/th?id=OIP.ge36cGMAI6uqFsjT_cIfwAHaHa&pid=Api",
      "alt": "Asus ExpertCenter D500SA",
      "description": "Bộ vi xử lý: Intel Core i5-10500, RAM: 8GB DDR4, Ổ cứng: SSD 256GB."
  },
  {
      "id": 6,
      "title": "HP EliteDesk 800 G6",
      "price": "20.000.000₫",
      "rating": "★★★★★",
      "image": "https://tse1.mm.bing.net/th?id=OIP.hWDC29ml-uN90AWtia2nfAHaHa&pid=Api",
      "alt": "HP EliteDesk 800 G6",
      "description": "Bộ vi xử lý: Intel Core i7-10700, RAM: 16GB DDR4, Ổ cứng: SSD 512GB."
  },
  {
      "id": 7,
      "title": "Dell OptiPlex 7080",
      "price": "22.000.000₫",
      "rating": "★★★★★",
      "image": "https://tse3.mm.bing.net/th?id=OIP.yfnJXeCq8hQudPBUeuETKgHaHa&pid=Api",
      "alt": "Dell OptiPlex 7080",
      "description": "Bộ vi xử lý: Intel Core i7-10700, RAM: 16GB DDR4, Ổ cứng: SSD 512GB."
  },
  {
      "id": 8,
      "title": "Lenovo ThinkCentre M920s",
      "price": "21.000.000₫",
      "rating": "★★★★★",
      "image": "https://tse2.mm.bing.net/th?id=OIP.2HjEwwt3zzQhYpgWpQDR_wHaHa&pid=Api",
      "alt": "Lenovo ThinkCentre M920s",
      "description": "Bộ vi xử lý: Intel Core i7-10700, RAM: 16GB DDR4, Ổ cứng: SSD 512GB."
  },
  {
      "id": 9,
      "title": "Acer Veriton X",
      "price": "19.000.000₫",
      "rating": "★★★★☆",
      "image": "https://tse3.mm.bing.net/th?id=OIP.N0xFOcnhNy5P0RKX1mCQ4gHaHa&pid=Api",
      "alt": "Acer Veriton X",
      "description": "Bộ vi xử lý: Intel Core i7-10700, RAM: 16GB DDR4, Ổ cứng: SSD 512GB."
  },
  {
      "id": 10,
      "title": "HP EliteDesk 800 G6",
      "price": "15.000.000₫",
      "rating": "★★★★☆",
      "image": "https://tse1.mm.bing.net/th?id=OIP.hWDC29ml-uN90AWtia2nfAHaHa&pid=Api",
      "alt": "HP EliteDesk 800 G6",
      "description": "Bộ vi xử lý: Intel Core i5-10500, RAM: 8GB DDR4, Ổ cứng: SSD 256GB."
  },
  {
    "id": 11,
    "title": "Dell OptiPlex 7080",
    "price": "16.500.000₫",
    "rating": "★★★★☆",
    "image": "https://tse3.mm.bing.net/th?id=OIP.yfnJXeCq8hQudPBUeuETKgHaHa&pid=Api",
    "alt": "Dell OptiPlex 7080",
    "description": "Bộ vi xử lý: Intel Core i5-10500, RAM: 8GB DDR4, Ổ cứng: SSD 256GB."
},
{
    "id": 12,
    "title": "Lenovo ThinkCentre M920s",
    "price": "15.500.000₫",
    "rating": "★★★★☆",
    "image": "https://tse2.mm.bing.net/th?id=OIP.2HjEwwt3zzQhYpgWpQDR_wHaHa&pid=Api",
    "alt": "Lenovo ThinkCentre M920s",
    "description": "Bộ vi xử lý: Intel Core i5-10500, RAM: 8GB DDR4, Ổ cứng: SSD 256GB."
},
{
    "id": 13,
    "title": "Acer Veriton X",
    "price": "11.500.000₫",
    "rating": "★★★☆☆",
    "image": "https://tse3.mm.bing.net/th?id=OIP.N0xFOcnhNy5P0RKX1mCQ4gHaHa&pid=Api",
    "alt": "Acer Veriton X",
    "description": "Bộ vi xử lý: Intel Core i5-10500, RAM: 8GB DDR4, Ổ cứng: SSD 256GB."
},
{
    "id": 14,
    "title": "Asus ExpertCenter D500SA",
    "price": "12.500.000₫",
    "rating": "★★★★☆",
    "image": "https://tse1.mm.bing.net/th?id=OIP.ge36cGMAI6uqFsjT_cIfwAHaHa&pid=Api",
    "alt": "Asus ExpertCenter D500SA",
    "description": "Bộ vi xử lý: Intel Core i5-10500, RAM: 8GB DDR4, Ổ cứng: SSD 256GB."
},
{
    "id": 15,
    "title": "HP EliteDesk 800 G6",
    "price": "18.000.000₫",
    "rating": "★★★★★",
    "image": "https://tse1.mm.bing.net/th?id=OIP.hWDC29ml-uN90AWtia2nfAHaHa&pid=Api",
    "alt": "HP EliteDesk 800 G6",
    "description": "Bộ vi xử lý: Intel Core i7-10700, RAM: 16GB DDR4, Ổ cứng: SSD 512GB."
},
{
    "id": 16,
    "title": "Dell OptiPlex 7080",
    "price": "20.500.000₫",
    "rating": "★★★★☆",
    "image": "https://tse3.mm.bing.net/th?id=OIP.yfnJXeCq8hQudPBUeuETKgHaHa&pid=Api",
    "alt": "Dell OptiPlex 7080",
    "description": "Bộ vi xử lý: Intel Core i7-10700, RAM: 16GB DDR4, Ổ cứng: SSD 512GB."
},
{
    "id": 17,
    "title": "Lenovo ThinkCentre M920s",
    "price": "22.000.000₫",
    "rating": "★★★★★",
    "image": "https://tse2.mm.bing.net/th?id=OIP.2HjEwwt3zzQhYpgWpQDR_wHaHa&pid=Api",
    "alt": "Lenovo ThinkCentre M920s",
    "description": "Bộ vi xử lý: Intel Core i7-10700, RAM: 16GB DDR4, Ổ cứng: SSD 512GB."
},
{
    "id": 18,
    "title": "Acer Veriton X",
    "price": "14.000.000₫",
    "rating": "★★★★☆",
    "image": "https://tse3.mm.bing.net/th?id=OIP.N0xFOcnhNy5P0RKX1mCQ4gHaHa&pid=Api",
    "alt": "Acer Veriton X",
    "description": "Bộ vi xử lý: Intel Core i5-10500, RAM: 8GB DDR4, Ổ cứng: SSD 256GB."
},
{
    "id": 19,
    "title": "Asus ExpertCenter D500SA",
    "price": "15.500.000₫",
    "rating": "★★★★☆",
    "image": "https://tse1.mm.bing.net/th?id=OIP.ge36cGMAI6uqFsjT_cIfwAHaHa&pid=Api",
    "alt": "Asus ExpertCenter D500SA",
    "description": "Bộ vi xử lý: Intel Core i5-10500, RAM: 8GB DDR4, Ổ cứng: SSD 256GB."
},
{
    "id": 20,
    "title": "HP EliteDesk 800 G6",
    "price": "17.500.000₫",
    "rating": "★★★★☆",
    "image": "https://tse1.mm.bing.net/th?id=OIP.hWDC29ml-uN90AWtia2nfAHaHa&pid=Api",
    "alt": "HP EliteDesk 800 G6",
    "description": "Bộ vi xử lý: Intel Core i5-10500, RAM: 8GB DDR4, Ổ cứng: SSD 256GB."
}
]
